mcp_server_datahub/__init__.py
mcp_server_datahub/__main__.py
mcp_server_datahub/_telemetry.py
mcp_server_datahub/_token_estimator.py
mcp_server_datahub/_version.py
mcp_server_datahub/mcp_server.py
mcp_server_datahub/py.typed
mcp_server_datahub/gql/entity_details.gql
mcp_server_datahub/gql/queries.gql
mcp_server_datahub/gql/query_entity.gql
mcp_server_datahub/gql/search.gql
mcp_server_datahub/gql/semantic_search.gql
mcp_server_datahub/gql/smart_search.gql
mcp_server_datahub-0.4.0.dist-info/licenses/LICENSE
mcp_server_datahub-0.4.0.dist-info/METADATA
mcp_server_datahub-0.4.0.dist-info/WHEEL
mcp_server_datahub-0.4.0.dist-info/entry_points.txt
mcp_server_datahub-0.4.0.dist-info/top_level.txt
mcp_server_datahub-0.4.0.dist-info/RECORD
